MANIFEST.in
README.rst
setup.py
jsonpath_ig/__init__.py
jsonpath_ig/exceptions.py
jsonpath_ig/jsonpath.py
jsonpath_ig/lexer.py
jsonpath_ig/parser.py
jsonpath_ig.egg-info/PKG-INFO
jsonpath_ig.egg-info/SOURCES.txt
jsonpath_ig.egg-info/dependency_links.txt
jsonpath_ig.egg-info/entry_points.txt
jsonpath_ig.egg-info/requires.txt
jsonpath_ig.egg-info/top_level.txt
jsonpath_ig/bin/__init__.py
jsonpath_ig/bin/jsonpath.py
jsonpath_ig/ext/__init__.py
jsonpath_ig/ext/arithmetic.py
jsonpath_ig/ext/filter.py
jsonpath_ig/ext/iterable.py
jsonpath_ig/ext/parser.py
jsonpath_ig/ext/string.py
tests/__init__.py
tests/test_examples.py
tests/test_exceptions.py
tests/test_jsonpath.py
tests/test_jsonpath_rw_ext.py
tests/test_lexer.py
tests/test_parser.py
tests/bin/__init__.py
tests/bin/test1.json
tests/bin/test2.json
tests/bin/test_jsonpath.py