Metadata-Version: 1.1
Name: jsonpath-ig
Version: 1.5.3
Summary: A final implementation of JSONPath for Python that aims to be standard compliant, including arithmetic and binary comparison operators and providing clear AST for metaprogramming.
Home-page: https://github.com/h2non/jsonpath-ng
Author: Tomas Aparicio
Author-email: tomas@aparicio.me
License: Apache 2.0
Platform: UNKNOWN
Classifier: Development Status :: 5 - Production/Stable
Classifier: Intended Audience :: Developers
Classifier: License :: OSI Approved :: Apache Software License
Classifier: Programming Language :: Python :: 2.7
Classifier: Programming Language :: Python :: 3
Classifier: Programming Language :: Python :: 3.5
Classifier: Programming Language :: Python :: 3.6
Classifier: Programming Language :: Python :: 3.7
Classifier: Programming Language :: Python :: 3.8
